idf_install/__init__.py
idf_install/cli.py
idf_install/install_idf.bat
idf_install/install_idf.py
idf_install/install_idf_repo.py
idf_install/platform_install.py
idf_install/settings.py
idf_install/util.py
idf_install/assets/example.txt
idf_install-1.0.5.dist-info/LICENSE
idf_install-1.0.5.dist-info/METADATA
idf_install-1.0.5.dist-info/WHEEL
idf_install-1.0.5.dist-info/entry_points.txt
idf_install-1.0.5.dist-info/top_level.txt
idf_install-1.0.5.dist-info/RECORD
