Metadata-Version: 2.1
Name: idf-install
Version: 1.0.5
Summary: Installs the idf toolchain for esp32 developement, targetting platformio
Home-page: https://github.com/zackees/idf-install
Maintainer: Zachary Vorhies
License: BSD 3-Clause License
Keywords: template-python-cmd
Classifier: Programming Language :: Python :: 3
Requires-Python: >=3.7
License-File: LICENSE
Requires-Dist: send2trash
